LICENSE
README.md
setup.py
HDRutils/__init__.py
HDRutils/capture.py
HDRutils/deglare.py
HDRutils/exposures.py
HDRutils/graphs.py
HDRutils/io.py
HDRutils/merge.py
HDRutils/utils.py
HDRutils.egg-info/PKG-INFO
HDRutils.egg-info/SOURCES.txt
HDRutils.egg-info/dependency_links.txt
HDRutils.egg-info/entry_points.txt
HDRutils.egg-info/requires.txt
HDRutils.egg-info/top_level.txt
HDRutils/noise_modeling/__init__.py
HDRutils/noise_modeling/darktable.json
HDRutils/noise_modeling/simulate.py