Metadata-Version: 2.1
Name: HDRutils
Version: 1.2
Summary: Utility functions for performing basic operations on HDR images, including merging and deghosting
Home-page: https://github.com/gfxdisp/HDRutils
Author: Param Hanji
Author-email: param.hanji@gmail.com
License: MIT
Keywords: HDR,Merging,Deghosting,simulation,exposure
Classifier: Development Status :: 3 - Alpha
Classifier: Intended Audience :: Developers
Classifier: Topic :: Software Development :: Build Tools
Classifier: License :: OSI Approved :: MIT License
Classifier: Programming Language :: Python :: 3.7
Classifier: Programming Language :: Python :: 3.8
Classifier: Programming Language :: Python :: 3.9
Classifier: Programming Language :: Python :: 3.10
Classifier: Programming Language :: Python :: 3.11
Classifier: Programming Language :: Python :: 3.12
License-File: LICENSE
Requires-Dist: numpy
Requires-Dist: imageio>=2.21.2
Requires-Dist: rawpy
Requires-Dist: exifread
Requires-Dist: tqdm
Requires-Dist: colour-demosaicing
Requires-Dist: matplotlib
Requires-Dist: scipy>=1.7.1
Requires-Dist: scikit-image>=0.18.3
Requires-Dist: pyexr
